curies_rs-0.1.3.dist-info/METADATA
curies_rs-0.1.3.dist-info/WHEEL
curies_rs-0.1.3.dist-info/license_files/LICENSE
curies_rs/__init__.py
curies_rs/curies_rs.cpython-39-darwin.so
curies_rs-0.1.3.dist-info/RECORD
