Metadata-Version: 2.1
Name: curies-rs
Version: 0.1.3
Classifier: Development Status :: 3 - Alpha
Classifier: Intended Audience :: Developers
Classifier: License :: OSI Approved :: MIT License
Classifier: Programming Language :: Python :: 3 :: Only
Classifier: Programming Language :: Python :: 3.8
Classifier: Programming Language :: Python :: 3.9
Classifier: Programming Language :: Python :: 3.10
Classifier: Programming Language :: Python :: 3.11
Classifier: Programming Language :: Python :: 3.12
Classifier: Programming Language :: Rust
Classifier: Topic :: Software Development :: Libraries :: Python Modules
License-File: LICENSE
Summary: Python bindings for the curies library
Keywords: semantic-web,linked-data,linked-open-data
Home-Page: https://biopragmatics.github/curies.rs
Author: Charles Tapley Hoyt <cthoyt@gmail.com>, Vincent Emonet <vincent.emonet@gmail.com>
Author-email: Charles Tapley Hoyt <cthoyt@gmail.com>, Vincent Emonet <vincent.emonet@gmail.com>
Requires-Python: >=3.8
Project-URL: Changelog, https://github.com/biopragmatics/curies.rs/blob/main/CHANGELOG.md
Project-URL: Documentation, https://biopragmatics.github.io/curies.rs
Project-URL: Homepage, https://biopragmatics.github.io/curies.rs
Project-URL: Source, https://github.com/biopragmatics/curies.rs/tree/main/python
Project-URL: Tracker, https://github.com/biopragmatics/curies.rs/issues
